tcpb_trio/__init__.py
tcpb_trio/_version.py
tcpb_trio/client.py
tcpb_trio/client_sync.py
tcpb_trio/conn.py
tcpb_trio/input.py
tcpb_trio/util.py
tcpb_trio/msg/__init__.py
tcpb_trio/msg/terachem_server_pb2.py
tcpb_trio-0.1.2.dist-info/METADATA
tcpb_trio-0.1.2.dist-info/WHEEL
tcpb_trio-0.1.2.dist-info/top_level.txt
tcpb_trio-0.1.2.dist-info/RECORD
