Metadata-Version: 2.2
Name: tcpb-trio
Version: 0.1.2
Requires-Python: >=3.10
Requires-Dist: protobuf>=3.20
Requires-Dist: trio
Requires-Dist: numpy
Provides-Extra: dev
Requires-Dist: grpcio-tools; extra == "dev"
Requires-Dist: black; extra == "dev"
Requires-Dist: pre-commit; extra == "dev"
Requires-Dist: build; extra == "dev"
Requires-Dist: twine; extra == "dev"
Dynamic: provides-extra
Dynamic: requires-dist
Dynamic: requires-python
